stelar_spatiotemporal/__init__.py
stelar_spatiotemporal/eopatch_functions.py
stelar_spatiotemporal/io.py
stelar_spatiotemporal/lib.py
stelar_spatiotemporal/data_fusion/__init__.py
stelar_spatiotemporal/data_fusion/coregistration.py
stelar_spatiotemporal/data_fusion/helpers.py
stelar_spatiotemporal/eoflow/__init__.py
stelar_spatiotemporal/eoflow/execute.py
stelar_spatiotemporal/eoflow/base/__init__.py
stelar_spatiotemporal/eoflow/base/base_input.py
stelar_spatiotemporal/eoflow/base/base_model.py
stelar_spatiotemporal/eoflow/base/base_task.py
stelar_spatiotemporal/eoflow/base/configuration.py
stelar_spatiotemporal/eoflow/input/__init__.py
stelar_spatiotemporal/eoflow/input/eopatch.py
stelar_spatiotemporal/eoflow/input/hdf5.py
stelar_spatiotemporal/eoflow/input/numpy.py
stelar_spatiotemporal/eoflow/input/operations.py
stelar_spatiotemporal/eoflow/input/random.py
stelar_spatiotemporal/eoflow/models/__init__.py
stelar_spatiotemporal/eoflow/models/callbacks.py
stelar_spatiotemporal/eoflow/models/classification_base.py
stelar_spatiotemporal/eoflow/models/classification_temp_nets.py
stelar_spatiotemporal/eoflow/models/layers.py
stelar_spatiotemporal/eoflow/models/losses.py
stelar_spatiotemporal/eoflow/models/metrics.py
stelar_spatiotemporal/eoflow/models/pse_tae_layers.py
stelar_spatiotemporal/eoflow/models/segmentation_base.py
stelar_spatiotemporal/eoflow/models/segmentation_unets.py
stelar_spatiotemporal/eoflow/models/transformer_encoder_layers.py
stelar_spatiotemporal/eoflow/tasks/__init__.py
stelar_spatiotemporal/eoflow/tasks/evaluate.py
stelar_spatiotemporal/eoflow/tasks/predict.py
stelar_spatiotemporal/eoflow/tasks/train.py
stelar_spatiotemporal/eoflow/utils/__init__.py
stelar_spatiotemporal/eoflow/utils/tf_utils.py
stelar_spatiotemporal/eoflow/utils/utils.py
stelar_spatiotemporal/eolearn/__init__.py
stelar_spatiotemporal/eolearn/core/__init__.py
stelar_spatiotemporal/eolearn/core/constants.py
stelar_spatiotemporal/eolearn/core/core_tasks.py
stelar_spatiotemporal-0.0.33.dist-info/licenses/LICENSE
stelar_spatiotemporal-0.0.33.dist-info/METADATA
stelar_spatiotemporal-0.0.33.dist-info/WHEEL
stelar_spatiotemporal-0.0.33.dist-info/top_level.txt
stelar_spatiotemporal-0.0.33.dist-info/RECORD
