Metadata-Version: 2.4
Name: stelar_spatiotemporal
Version: 0.0.33
Summary: Spatiotemporal data processing for the STELAR project
Author: Jens d'Hondt
Author-email: j.e.d.hondt@tue.nl
Classifier: Development Status :: 3 - Alpha
Classifier: Programming Language :: Python :: 3
Classifier: Operating System :: OS Independent
License-File: LICENSE
Requires-Dist: pystac
Requires-Dist: pystac_client
Requires-Dist: shapely
Requires-Dist: opencv-python
Requires-Dist: numpy
Requires-Dist: sentinelhub
Requires-Dist: pandas
Requires-Dist: rasterio
Requires-Dist: geopandas>=0.8.1
Requires-Dist: decorator
Requires-Dist: scikit-image
Requires-Dist: fs
Requires-Dist: fs-s3fs
Requires-Dist: s3fs
Requires-Dist: tqdm
Requires-Dist: boto3
Requires-Dist: matplotlib
Requires-Dist: fiona
Dynamic: author
Dynamic: author-email
Dynamic: classifier
Dynamic: description
Dynamic: license-file
Dynamic: requires-dist
Dynamic: summary
